intervallum/__init__.py
intervallum/box.py
intervallum/box_functions.py
intervallum/inclusion_functions.py
intervallum/interval.py
intervallum/interval_functions.py
intervallum-0.2.6.dist-info/DESCRIPTION.rst
intervallum-0.2.6.dist-info/METADATA
intervallum-0.2.6.dist-info/RECORD
intervallum-0.2.6.dist-info/WHEEL
intervallum-0.2.6.dist-info/metadata.json
intervallum-0.2.6.dist-info/top_level.txt
